pywilight/__init__.py
pywilight/const.py
pywilight/discovery.py
pywilight/ssdp.py
pywilight/subscribe.py
pywilight/util.py
pywilight/wilight_device/__init__.py
pywilight/wilight_device/protocol.py
pywilight/wilight_device/protocol_ex.py
pywilight/wilight_device/support.py
pywilight/wilight_device/api/__init__.py
pywilight/wilight_device/api/xsd/__init__.py
pywilight/wilight_device/api/xsd/device.py
pywilight-0.0.74.dist-info/LICENSE
pywilight-0.0.74.dist-info/METADATA
pywilight-0.0.74.dist-info/WHEEL
pywilight-0.0.74.dist-info/top_level.txt
pywilight-0.0.74.dist-info/RECORD
