Metadata-Version: 2.1
Name: pywilight
Version: 0.0.74
Summary: Python API for WiLight in Home Assistant
Home-page: https://github.com/leofig-rj/pywilight
Author: Leonardo Figueiro
Author-email: leoagfig@gmail.com
License: UNKNOWN
Platform: UNKNOWN
Classifier: Programming Language :: Python :: 3
Classifier: License :: OSI Approved :: MIT License
Classifier: Operating System :: OS Independent
Requires-Python: >=3.8
